rccgeoviz/__init__.py
rccgeoviz/geoviz_cli.py
rccgeoviz-0.0.1.dist-info/METADATA
rccgeoviz-0.0.1.dist-info/WHEEL
rccgeoviz-0.0.1.dist-info/entry_points.txt
rccgeoviz-0.0.1.dist-info/top_level.txt
rccgeoviz-0.0.1.dist-info/RECORD
