Metadata-Version: 2.1
Name: rccgeoviz
Version: 0.0.1
Summary: EDA tool for spatio-temporal data
Author-email: Jonas Nielsen <bobthebuilder.chfi@gmail.com>, Daniel Millward <dfmillward02@gmail.com>, Stephen Tveten  <stveten@student.byu.edu>
Project-URL: Documentation, https://rincon-geoviz.readthedocs.io/en/latest/index.html
Project-URL: Homepage, https://github.com/rrc-byu/ds-capstone-2023-2024
Requires-Python: >=3.9
Requires-Dist: panel
Requires-Dist: pandas
Requires-Dist: numpy
